oracle_utils/__init__.py
oracle_utils/config_query.py
oracle_utils/db_config.py
oracle_utils/oracle_utils.py
oracle_utils/rman_script.py
oracle_utils-1.1.1.dist-info/METADATA
oracle_utils-1.1.1.dist-info/WHEEL
oracle_utils-1.1.1.dist-info/entry_points.txt
oracle_utils-1.1.1.dist-info/licenses/LICENSE.txt
oracle_utils-1.1.1.dist-info/RECORD
