Metadata-Version: 2.4
Name: oracle_utils
Version: 1.1.1
Summary: Oracle SQLPlus Automation for Database Scripting
Project-URL: Homepage, https://github.com/mminichino/oracle-scripts/tree/master/src
Author-email: Michael Minichino <info@unix.us.com>
License-Expression: MIT
License-File: LICENSE.txt
Keywords: automation,backup,database,oracle,sqlplus
Classifier: Development Status :: 5 - Production/Stable
Classifier: Intended Audience :: Developers
Classifier: License :: OSI Approved :: MIT License
Classifier: Operating System :: OS Independent
Classifier: Programming Language :: Python
Classifier: Programming Language :: Python :: 3
Classifier: Topic :: Database
Classifier: Topic :: Software Development :: Libraries
Classifier: Topic :: Software Development :: Libraries :: Python Modules
Requires-Python: >=3.8
